hkl/__init__.py
hkl/calc.py
hkl/configuration.py
hkl/context.py
hkl/diffract.py
hkl/engine.py
hkl/geometries.py
hkl/sample.py
hkl/user.py
hkl/util.py
hkl/tests/__init__.py
hkl/tests/common.py
hkl/tests/conftest.py
hkl/tests/test_configuration.py
hkl/tests/test_diffract.py
hkl/tests/test_extra_motor.py
hkl/tests/test_fourc.py
hkl/tests/test_i307.py
hkl/tests/test_i325_motor_config_attrs.py
hkl/tests/test_i350_value-error.py
hkl/tests/test_init.py
hkl/tests/test_restore_reflections.py
hkl/tests/test_sample.py
hkl/tests/test_save_restore_UB.py
hkl/tests/test_tardis.py
hkl/tests/test_user.py
hkl/tests/test_util.py
hkl/tests/tools.py
hkl/tests/data/e4c-config.json
hklpy-1.1.2.dist-info/licenses/LICENSE
hklpy-1.1.2.dist-info/METADATA
hklpy-1.1.2.dist-info/WHEEL
hklpy-1.1.2.dist-info/top_level.txt
hklpy-1.1.2.dist-info/RECORD
