Metadata-Version: 2.4
Name: hklpy
Version: 1.1.2
Summary: Controls for using diffractometers within the Bluesky Framework.
Author: Ken Lauer, Max Rakitin
Author-email: Pete Jemian <prjemian+hklpy@gmail.com>
Maintainer-email: Pete Jemian <prjemian+hklpy@gmail.com>
License: BSD 3-Clause License
Project-URL: Homepage, https://blueskyproject.io/hklpy/
Project-URL: Bug Tracker, https://github.com/bluesky/hklpy/issues
Keywords: bluesky,diffraction,diffractometer
Classifier: Development Status :: 5 - Production/Stable
Classifier: Environment :: Console
Classifier: Intended Audience :: Science/Research
Classifier: License :: Freely Distributable
Classifier: License :: Public Domain
Classifier: Operating System :: OS Independent
Classifier: Programming Language :: Python :: 3.11
Classifier: Programming Language :: Python :: 3.10
Classifier: Programming Language :: Python :: 3.9
Classifier: Programming Language :: Python :: 3.8
Classifier: Programming Language :: Python :: 3
Classifier: Programming Language :: Python
Classifier: Topic :: Scientific/Engineering :: Astronomy
Classifier: Topic :: Scientific/Engineering :: Bio-Informatics
Classifier: Topic :: Scientific/Engineering :: Chemistry
Classifier: Topic :: Scientific/Engineering :: Mathematics
Classifier: Topic :: Scientific/Engineering :: Physics
Classifier: Topic :: Scientific/Engineering :: Visualization
Classifier: Topic :: Scientific/Engineering
Requires-Python: >=3.9
License-File: LICENSE
Requires-Dist: apischema
Requires-Dist: databroker
Requires-Dist: numpy
Requires-Dist: ophyd
Requires-Dist: orjson
Requires-Dist: pint
Requires-Dist: pygobject
Requires-Dist: pyRestTable
Requires-Dist: tqdm
Provides-Extra: docs
Requires-Dist: pydata-sphinx-theme; extra == "docs"
Requires-Dist: spec2nexus; extra == "docs"
Provides-Extra: tests
Requires-Dist: bluesky; extra == "tests"
Requires-Dist: coveralls; extra == "tests"
Requires-Dist: databroker<=1.999; extra == "tests"
Requires-Dist: numpy<=1.999; extra == "tests"
Requires-Dist: orjson; extra == "tests"
Requires-Dist: packaging; extra == "tests"
Requires-Dist: pytest-cov; extra == "tests"
Requires-Dist: pytest; extra == "tests"
Provides-Extra: all
Requires-Dist: hklpy[docs,tests]; extra == "all"
Dynamic: license-file
